{"title":"Agreement","content":"The agreement interface is a modal sub-interface that is displayed to players when they first open the choose a slot interface.\n\nIt contains links to the game rules, terms and conditions, and privacy notice interfaces. To continue with the character creation, the player must confirm that they have read all these and that they agree to the beginning of the supply of services that the game offers.\n\n\n\n","tables":[],"url":"https://brightershoreswiki.org/w/Agreement","last_modified":"2024-11-09T06:36:11Z","categories":["Category:Incomplete articles","Category:Interface","Category:Pages with update history"]}