{"title":"Seashells Seashore","content":"Seashells Seashore is a location in Hopeport. It connects to the East Beach in the east and the Jellyfish Landing in the west. Shells and a Rock Pool can be found on the beach.\n\n\n\n\n * This location is most likely named after the well-known \"she sells seashells by the seashore\".\n\n\n\n","tables":[],"url":"https://brightershoreswiki.org/w/Seashells_Seashore","last_modified":"2024-11-09T05:35:47Z","categories":["Category:Pages with broken file links","Category:Pages with update history","Category:Rooms"]}